squishie/__init__.py
squishie/__main__.py
squishie/_version.py
squishie/builder.py
squishie/main.py
squishie/models.py
squishie/serializers.py
squishie-0.5.2.dist-info/licenses/LICENSE
squishie-0.5.2.dist-info/licenses/NOTICE
squishie-0.5.2.dist-info/METADATA
squishie-0.5.2.dist-info/WHEEL
squishie-0.5.2.dist-info/entry_points.txt
squishie-0.5.2.dist-info/top_level.txt
squishie-0.5.2.dist-info/RECORD
