Metadata-Version: 2.4
Name: squishie
Version: 0.5.2
Summary: Squish multiple Pandoc-flavored Markdown files into one super squished document.
Author-email: Digital Safety Research Institute <contact@dsri.org>
License: Apache-2.0
Project-URL: Home, https://gitlab.com/saferatday0/sandbox/squishie
Project-URL: Issues, https://gitlab.com/saferatday0/sandbox/squishie/-/issues
Keywords: pandoc,markdown,documentation
Classifier: Development Status :: 1 - Planning
Classifier: Intended Audience :: Developers
Classifier: Topic :: Software Development :: Documentation
Classifier: Programming Language :: Python :: 3
Classifier: Programming Language :: Python :: 3.8
Classifier: Programming Language :: Python :: 3.9
Classifier: Programming Language :: Python :: 3.10
Classifier: Programming Language :: Python :: 3.11
Classifier: Programming Language :: Python :: 3.12
Requires-Python: >=3.8
License-File: LICENSE
License-File: NOTICE
Requires-Dist: attrs
Requires-Dist: cattrs
Requires-Dist: python-frontmatter
Requires-Dist: pyyaml
Dynamic: license-file
